llmgatekeeper/__init__.py
llmgatekeeper/analytics.py
llmgatekeeper/cache.py
llmgatekeeper/exceptions.py
llmgatekeeper/logging.py
llmgatekeeper/backends/__init__.py
llmgatekeeper/backends/base.py
llmgatekeeper/backends/factory.py
llmgatekeeper/backends/redis_async.py
llmgatekeeper/backends/redis_search.py
llmgatekeeper/backends/redis_simple.py
llmgatekeeper/embeddings/__init__.py
llmgatekeeper/embeddings/base.py
llmgatekeeper/embeddings/cached.py
llmgatekeeper/embeddings/openai_provider.py
llmgatekeeper/embeddings/sentence_transformer.py
llmgatekeeper/similarity/__init__.py
llmgatekeeper/similarity/confidence.py
llmgatekeeper/similarity/metrics.py
llmgatekeeper/similarity/retriever.py
llmgatekeeper-0.1.0.dist-info/licenses/LICENSE
llmgatekeeper-0.1.0.dist-info/METADATA
llmgatekeeper-0.1.0.dist-info/WHEEL
llmgatekeeper-0.1.0.dist-info/top_level.txt
llmgatekeeper-0.1.0.dist-info/RECORD
