Metadata-Version: 2.4
Name: llmgatekeeper
Version: 0.1.0
Summary: Semantic caching library for LLM and RAG systems
Author: LLMGatekeeper Contributors
License: MIT
Project-URL: Homepage, https://github.com/llmgatekeeper/llmgatekeeper
Project-URL: Documentation, https://github.com/llmgatekeeper/llmgatekeeper#readme
Project-URL: Repository, https://github.com/llmgatekeeper/llmgatekeeper
Keywords: llm,cache,semantic,rag,embeddings,redis
Classifier: Development Status :: 3 - Alpha
Classifier: Intended Audience :: Developers
Classifier: License :: OSI Approved :: MIT License
Classifier: Programming Language :: Python :: 3
Classifier: Programming Language :: Python :: 3.9
Classifier: Programming Language :: Python :: 3.10
Classifier: Programming Language :: Python :: 3.11
Classifier: Programming Language :: Python :: 3.12
Classifier: Topic :: Software Development :: Libraries :: Python Modules
Requires-Python: >=3.9
License-File: LICENSE
Requires-Dist: redis>=4.0.0
Requires-Dist: numpy>=1.21.0
Requires-Dist: pydantic>=2.0.0
Requires-Dist: loguru>=0.7.0
Requires-Dist: sentence-transformers>=2.2.0
Provides-Extra: openai
Requires-Dist: openai>=1.0.0; extra == "openai"
Provides-Extra: dev
Requires-Dist: pytest>=7.0.0; extra == "dev"
Requires-Dist: pytest-asyncio>=0.21.0; extra == "dev"
Requires-Dist: pytest-cov>=4.0.0; extra == "dev"
Requires-Dist: black>=23.0.0; extra == "dev"
Requires-Dist: ruff>=0.1.0; extra == "dev"
Requires-Dist: mypy>=1.0.0; extra == "dev"
Provides-Extra: all
Requires-Dist: llmgatekeeper[dev,openai]; extra == "all"
Dynamic: license-file
